LICENSE.txt
README.md
setup.cfg
setup.py
twtlib/__init__.py
twtlib/twtlib.py
twtlib.egg-info/PKG-INFO
twtlib.egg-info/SOURCES.txt
twtlib.egg-info/dependency_links.txt
twtlib.egg-info/top_level.txt