Metadata-Version: 1.0
Name: twtlib
Version: 1.0.0
Summary: Lib to search and post on Twitter
Home-page: https://github.com/ribeiro-daniel/Twtlib
Author: Daniel Ribeiro
Author-email: UNKNOWN
License: MIT
Keywords: Search and Post on Twitter,Buscar e Postar no Twitter
Platform: UNKNOWN
